[
    {
        "id":1,"imgurl":"../img/1.jpg","title":"特步官方店年前特卖专场","pro":"年终特惠，低价嗨购","pingpai":"收藏品牌"
    },{
        "id":2,"imgurl":"../img/1.jpg","title":"特步官方店年前特卖专场","pro":"年终特惠，低价嗨购","pingpai":"收藏品牌"
    },{
        "id":3,"imgurl":"../img/1.jpg","title":"特步官方店年前特卖专场","pro":"年终特惠，低价嗨购","pingpai":"收藏品牌"
    },{
        "id":4,"imgurl":"../img/1.jpg","title":"特步官方店年前特卖专场","pro":"年终特惠，低价嗨购","pingpai":"收藏品牌"
    },{
        "id":5,"imgurl":"../img/1.jpg","title":"特步官方店年前特卖专场","pro":"年终特惠，低价嗨购","pingpai":"收藏品牌"
    },{
        "id":6,"imgurl":"../img/1.jpg","title":"特步官方店年前特卖专场","pro":"年终特惠，低价嗨购","pingpai":"收藏品牌"
    },{
        "id":7,"imgurl":"../img/1.jpg","title":"特步官方店年前特卖专场","pro":"年终特惠，低价嗨购","pingpai":"收藏品牌"
    },{
        "id":8,"imgurl":"../img/1.jpg","title":"特步官方店年前特卖专场","pro":"年终特惠，低价嗨购","pingpai":"收藏品牌"
    },{
        "id":9,"imgurl":"../img/1.jpg","title":"特步官方店年前特卖专场","pro":"年终特惠，低价嗨购","pingpai":"收藏品牌"
    },{
        "id":10,"imgurl":"../img/1.jpg","title":"特步官方店年前特卖专场","pro":"年终特惠，低价嗨购","pingpai":"收藏品牌"
    },{
        "id":11,"imgurl":"../img/1.jpg","title":"特步官方店年前特卖专场","pro":"年终特惠，低价嗨购","pingpai":"收藏品牌"
    },{
        "id":12,"imgurl":"../img/1.jpg","title":"特步官方店年前特卖专场","pro":"年终特惠，低价嗨购","pingpai":"收藏品牌"
    },{
        "id":13,"imgurl":"../img/1.jpg","title":"特步官方店年前特卖专场","pro":"年终特惠，低价嗨购","pingpai":"收藏品牌"
    },{
        "id":14,"imgurl":"../img/1.jpg","title":"特步官方店年前特卖专场","pro":"年终特惠，低价嗨购","pingpai":"收藏品牌"
    },{
        "id":15,"imgurl":"../img/1.jpg","title":"特步官方店年前特卖专场","pro":"年终特惠，低价嗨购","pingpai":"收藏品牌"
    },{
        "id":16,"imgurl":"../img/1.jpg","title":"特步官方店年前特卖专场","pro":"年终特惠，低价嗨购","pingpai":"收藏品牌"
    },{
        "id":17,"imgurl":"../img/1.jpg","title":"特步官方店年前特卖专场","pro":"年终特惠，低价嗨购","pingpai":"收藏品牌"
    },{
        "id":18,"imgurl":"../img/1.jpg","title":"特步官方店年前特卖专场","pro":"年终特惠，低价嗨购","pingpai":"收藏品牌"
    },{
        "id":19,"imgurl":"../img/1.jpg","title":"特步官方店年前特卖专场","pro":"年终特惠，低价嗨购","pingpai":"收藏品牌"
    },{
        "id":20,"imgurl":"../img/1.jpg","title":"特步官方店年前特卖专场","pro":"年终特惠，低价嗨购","pingpai":"收藏品牌"
    },{
        "id":21,"imgurl":"../img/1.jpg","title":"特步官方店年前特卖专场","pro":"年终特惠，低价嗨购","pingpai":"收藏品牌"
    },{
        "id":22,"imgurl":"../img/1.jpg","title":"特步官方店年前特卖专场","pro":"年终特惠，低价嗨购","pingpai":"收藏品牌"
    },{
        "id":23,"imgurl":"../img/1.jpg","title":"特步官方店年前特卖专场","pro":"年终特惠，低价嗨购","pingpai":"收藏品牌"
    },{
        "id":18,"imgurl":"../img/1.jpg","title":"特步官方店年前特卖专场","pro":"年终特惠，低价嗨购","pingpai":"收藏品牌"
    },{
        "id":24,"imgurl":"../img/1.jpg","title":"特步官方店年前特卖专场","pro":"年终特惠，低价嗨购","pingpai":"收藏品牌"
    },{
        "id":25,"imgurl":"../img/1.jpg","title":"特步官方店年前特卖专场","pro":"年终特惠，低价嗨购","pingpai":"收藏品牌"
    },{
        "id":26,"imgurl":"../img/1.jpg","title":"特步官方店年前特卖专场","pro":"年终特惠，低价嗨购","pingpai":"收藏品牌"
    },{
        "id":27,"imgurl":"../img/1.jpg","title":"特步官方店年前特卖专场","pro":"年终特惠，低价嗨购","pingpai":"收藏品牌"
    },{
        "id":28,"imgurl":"../img/1.jpg","title":"特步官方店年前特卖专场","pro":"年终特惠，低价嗨购","pingpai":"收藏品牌"
    },{
        "id":29,"imgurl":"../img/1.jpg","title":"特步官方店年前特卖专场","pro":"年终特惠，低价嗨购","pingpai":"收藏品牌"
    },{
        "id":30,"imgurl":"../img/1.jpg","title":"特步官方店年前特卖专场","pro":"年终特惠，低价嗨购","pingpai":"收藏品牌"
    },{
        "id":31,"imgurl":"../img/1.jpg","title":"特步官方店年前特卖专场","pro":"年终特惠，低价嗨购","pingpai":"收藏品牌"
    },{
        "id":32,"imgurl":"../img/1.jpg","title":"特步官方店年前特卖专场","pro":"年终特惠，低价嗨购","pingpai":"收藏品牌"
    },{
        "id":33,"imgurl":"../img/1.jpg","title":"特步官方店年前特卖专场","pro":"年终特惠，低价嗨购","pingpai":"收藏品牌"
    },{
        "id":34,"imgurl":"../img/1.jpg","title":"特步官方店年前特卖专场","pro":"年终特惠，低价嗨购","pingpai":"收藏品牌"
    },{
        "id":35,"imgurl":"../img/1.jpg","title":"特步官方店年前特卖专场","pro":"年终特惠，低价嗨购","pingpai":"收藏品牌"
    },{
        "id":36,"imgurl":"../img/1.jpg","title":"特步官方店年前特卖专场","pro":"年终特惠，低价嗨购","pingpai":"收藏品牌"
    },{
        "id":37,"imgurl":"../img/1.jpg","title":"特步官方店年前特卖专场","pro":"年终特惠，低价嗨购","pingpai":"收藏品牌"
    },{
        "id":38,"imgurl":"../img/1.jpg","title":"特步官方店年前特卖专场","pro":"年终特惠，低价嗨购","pingpai":"收藏品牌"
    },{
        "id":39,"imgurl":"../img/1.jpg","title":"特步官方店年前特卖专场","pro":"年终特惠，低价嗨购","pingpai":"收藏品牌"
    },{
        "id":40,"imgurl":"../img/1.jpg","title":"特步官方店年前特卖专场","pro":"年终特惠，低价嗨购","pingpai":"收藏品牌"
    },{
        "id":41,"imgurl":"../img/1.jpg","title":"特步官方店年前特卖专场","pro":"年终特惠，低价嗨购","pingpai":"收藏品牌"
    },{
        "id":42,"imgurl":"../img/1.jpg","title":"特步官方店年前特卖专场","pro":"年终特惠，低价嗨购","pingpai":"收藏品牌"
    },{
        "id":43,"imgurl":"../img/1.jpg","title":"特步官方店年前特卖专场","pro":"年终特惠，低价嗨购","pingpai":"收藏品牌"
    },{
        "id":44,"imgurl":"../img/1.jpg","title":"特步官方店年前特卖专场","pro":"年终特惠，低价嗨购","pingpai":"收藏品牌"
    },{
        "id":45,"imgurl":"../img/1.jpg","title":"特步官方店年前特卖专场","pro":"年终特惠，低价嗨购","pingpai":"收藏品牌"
    },{
        "id":46,"imgurl":"../img/1.jpg","title":"特步官方店年前特卖专场","pro":"年终特惠，低价嗨购","pingpai":"收藏品牌"
    },{
        "id":47,"imgurl":"../img/1.jpg","title":"特步官方店年前特卖专场","pro":"年终特惠，低价嗨购","pingpai":"收藏品牌"
    },{
        "id":48,"imgurl":"../img/1.jpg","title":"特步官方店年前特卖专场","pro":"年终特惠，低价嗨购","pingpai":"收藏品牌"
    },{
        "id":49,"imgurl":"../img/1.jpg","title":"特步官方店年前特卖专场","pro":"年终特惠，低价嗨购","pingpai":"收藏品牌"
    },{
        "id":50,"imgurl":"../img/1.jpg","title":"特步官方店年前特卖专场","pro":"年终特惠，低价嗨购","pingpai":"收藏品牌"
    },{
        "id":51,"imgurl":"../img/1.jpg","title":"特步官方店年前特卖专场","pro":"年终特惠，低价嗨购","pingpai":"收藏品牌"
    },{
        "id":52,"imgurl":"../img/1.jpg","title":"特步官方店年前特卖专场","pro":"年终特惠，低价嗨购","pingpai":"收藏品牌"
    },{
        "id":53,"imgurl":"../img/1.jpg","title":"特步官方店年前特卖专场","pro":"年终特惠，低价嗨购","pingpai":"收藏品牌"
    },{
        "id":54,"imgurl":"../img/1.jpg","title":"特步官方店年前特卖专场","pro":"年终特惠，低价嗨购","pingpai":"收藏品牌"
    },{
        "id":55,"imgurl":"../img/1.jpg","title":"特步官方店年前特卖专场","pro":"年终特惠，低价嗨购","pingpai":"收藏品牌"
    },{
        "id":56,"imgurl":"../img/1.jpg","title":"特步官方店年前特卖专场","pro":"年终特惠，低价嗨购","pingpai":"收藏品牌"
    },{
        "id":57,"imgurl":"../img/1.jpg","title":"特步官方店年前特卖专场","pro":"年终特惠，低价嗨购","pingpai":"收藏品牌"
    },{
        "id":58,"imgurl":"../img/1.jpg","title":"特步官方店年前特卖专场","pro":"年终特惠，低价嗨购","pingpai":"收藏品牌"
    },{
        "id":59,"imgurl":"../img/1.jpg","title":"特步官方店年前特卖专场","pro":"年终特惠，低价嗨购","pingpai":"收藏品牌"
    },{
        "id":60,"imgurl":"../img/1.jpg","title":"特步官方店年前特卖专场","pro":"年终特惠，低价嗨购","pingpai":"收藏品牌"
    },{
        "id":61,"imgurl":"../img/1.jpg","title":"特步官方店年前特卖专场","pro":"年终特惠，低价嗨购","pingpai":"收藏品牌"
    },{
        "id":62,"imgurl":"../img/1.jpg","title":"特步官方店年前特卖专场","pro":"年终特惠，低价嗨购","pingpai":"收藏品牌"
    },{
        "id":63,"imgurl":"../img/1.jpg","title":"特步官方店年前特卖专场","pro":"年终特惠，低价嗨购","pingpai":"收藏品牌"
    },{
        "id":64,"imgurl":"../img/1.jpg","title":"特步官方店年前特卖专场","pro":"年终特惠，低价嗨购","pingpai":"收藏品牌"
    },{
        "id":65,"imgurl":"../img/1.jpg","title":"特步官方店年前特卖专场","pro":"年终特惠，低价嗨购","pingpai":"收藏品牌"
    },{
        "id":66,"imgurl":"../img/1.jpg","title":"特步官方店年前特卖专场","pro":"年终特惠，低价嗨购","pingpai":"收藏品牌"
    },{
        "id":67,"imgurl":"../img/1.jpg","title":"特步官方店年前特卖专场","pro":"年终特惠，低价嗨购","pingpai":"收藏品牌"
    },{
        "id":68,"imgurl":"../img/1.jpg","title":"特步官方店年前特卖专场","pro":"年终特惠，低价嗨购","pingpai":"收藏品牌"
    },{
        "id":69,"imgurl":"../img/1.jpg","title":"特步官方店年前特卖专场","pro":"年终特惠，低价嗨购","pingpai":"收藏品牌"
    },{
        "id":70,"imgurl":"../img/1.jpg","title":"特步官方店年前特卖专场","pro":"年终特惠，低价嗨购","pingpai":"收藏品牌"
    },{
        "id":71,"imgurl":"../img/1.jpg","title":"特步官方店年前特卖专场","pro":"年终特惠，低价嗨购","pingpai":"收藏品牌"
    },{
        "id":72,"imgurl":"../img/1.jpg","title":"特步官方店年前特卖专场","pro":"年终特惠，低价嗨购","pingpai":"收藏品牌"
    },{
        "id":73,"imgurl":"../img/1.jpg","title":"特步官方店年前特卖专场","pro":"年终特惠，低价嗨购","pingpai":"收藏品牌"
    },{
        "id":74,"imgurl":"../img/1.jpg","title":"特步官方店年前特卖专场","pro":"年终特惠，低价嗨购","pingpai":"收藏品牌"
    },{
        "id":75,"imgurl":"../img/1.jpg","title":"特步官方店年前特卖专场","pro":"年终特惠，低价嗨购","pingpai":"收藏品牌"
    },{
        "id":76,"imgurl":"../img/1.jpg","title":"特步官方店年前特卖专场","pro":"年终特惠，低价嗨购","pingpai":"收藏品牌"
    },{
        "id":77,"imgurl":"../img/1.jpg","title":"特步官方店年前特卖专场","pro":"年终特惠，低价嗨购","pingpai":"收藏品牌"
    },{
        "id":78,"imgurl":"../img/1.jpg","title":"特步官方店年前特卖专场","pro":"年终特惠，低价嗨购","pingpai":"收藏品牌"
    },{
        "id":79,"imgurl":"../img/1.jpg","title":"特步官方店年前特卖专场","pro":"年终特惠，低价嗨购","pingpai":"收藏品牌"
    },{
        "id":80,"imgurl":"../img/1.jpg","title":"特步官方店年前特卖专场","pro":"年终特惠，低价嗨购","pingpai":"收藏品牌"
    },{
        "id":81,"imgurl":"../img/1.jpg","title":"特步官方店年前特卖专场","pro":"年终特惠，低价嗨购","pingpai":"收藏品牌"
    },{
        "id":82,"imgurl":"../img/1.jpg","title":"特步官方店年前特卖专场","pro":"年终特惠，低价嗨购","pingpai":"收藏品牌"
    },{
        "id":83,"imgurl":"../img/1.jpg","title":"特步官方店年前特卖专场","pro":"年终特惠，低价嗨购","pingpai":"收藏品牌"
    },{
        "id":84,"imgurl":"../img/1.jpg","title":"特步官方店年前特卖专场","pro":"年终特惠，低价嗨购","pingpai":"收藏品牌"
    },{
        "id":85,"imgurl":"../img/1.jpg","title":"特步官方店年前特卖专场","pro":"年终特惠，低价嗨购","pingpai":"收藏品牌"
    },{
        "id":86,"imgurl":"../img/1.jpg","title":"特步官方店年前特卖专场","pro":"年终特惠，低价嗨购","pingpai":"收藏品牌"
    },{
        "id":87,"imgurl":"../img/1.jpg","title":"特步官方店年前特卖专场","pro":"年终特惠，低价嗨购","pingpai":"收藏品牌"
    },{
        "id":88,"imgurl":"../img/1.jpg","title":"特步官方店年前特卖专场","pro":"年终特惠，低价嗨购","pingpai":"收藏品牌"
    },{
        "id":89,"imgurl":"../img/1.jpg","title":"特步官方店年前特卖专场","pro":"年终特惠，低价嗨购","pingpai":"收藏品牌"
    },{
        "id":90,"imgurl":"../img/1.jpg","title":"特步官方店年前特卖专场","pro":"年终特惠，低价嗨购","pingpai":"收藏品牌"
    },{
        "id":91,"imgurl":"../img/1.jpg","title":"特步官方店年前特卖专场","pro":"年终特惠，低价嗨购","pingpai":"收藏品牌"
    },{
        "id":92,"imgurl":"../img/1.jpg","title":"特步官方店年前特卖专场","pro":"年终特惠，低价嗨购","pingpai":"收藏品牌"
    },{
        "id":93,"imgurl":"../img/1.jpg","title":"特步官方店年前特卖专场","pro":"年终特惠，低价嗨购","pingpai":"收藏品牌"
    },{
        "id":94,"imgurl":"../img/1.jpg","title":"特步官方店年前特卖专场","pro":"年终特惠，低价嗨购","pingpai":"收藏品牌"
    }

]














